warthog/exceptions.py
warthog/api.py
warthog/transport.py
warthog/client.py
warthog/config.py
warthog/ssl.py
warthog/__init__.py
warthog/core.py
warthog/cli.py
warthog/packages/six.py
warthog/packages/__init__.py
warthog-2.0.1.dist-info/metadata.json
warthog-2.0.1.dist-info/METADATA
warthog-2.0.1.dist-info/WHEEL
warthog-2.0.1.dist-info/DESCRIPTION.rst
warthog-2.0.1.dist-info/zip-safe
warthog-2.0.1.dist-info/top_level.txt
warthog-2.0.1.dist-info/RECORD
warthog-2.0.1.dist-info/entry_points.txt
